{
  "version": 1,
  "system": "x86_64-linux",
  "virtualisation": "none",
  "hardware": {
    "bios": {
      "apm_info": {
        "supported": false,
        "enabled": false,
        "version": 0,
        "sub_version": 0,
        "bios_flags": 0
      },
      "vbe_info": {
        "version": 0,
        "video_memory": 0
      },
      "pnp": true,
      "pnp_id": 2389070,
      "lba_support": false,
      "low_memory_size": 649216,
      "smbios_version": 519
    },
    "bluetooth": [
      {
        "index": 27,
        "attached_to": 34,
        "class_list": [
          "usb",
          "bluetooth"
        ],
        "bus_type": {
          "hex": "0086",
          "name": "USB",
          "value": 134
        },
        "slot": {
          "bus": 0,
          "number": 0
        },
        "base_class": {
          "hex": "0115",
          "name": "Bluetooth Device",
          "value": 277
        },
        "vendor": {
          "hex": "8087",
          "value": 32903
        },
        "device": {
          "hex": "07dc",
          "value": 2012
        },
        "revision": {
          "hex": "0000",
          "name": "0.01",
          "value": 0
        },
        "model": "Bluetooth Device",
        "sysfs_id": "/devices/pci0000:00/0000:00:14.0/usb2/2-7/2-7:1.1",
        "sysfs_bus_id": "2-7:1.1",
        "resources": [
          {
            "type": "baud",
            "speed": 12000000,
            "bits": 0,
            "stop_bits": 0,
            "parity": 0,
            "handshake": 0
          }
        ],
        "detail": {
          "device_class": {
            "hex": "00e0",
            "name": "wireless",
            "value": 224
          },
          "device_subclass": {
            "hex": "0001",
            "name": "audio",
            "value": 1
          },
          "device_protocol": 1,
          "interface_class": {
            "hex": "00e0",
            "name": "wireless",
            "value": 224
          },
          "interface_subclass": {
            "hex": "0001",
            "name": "audio",
            "value": 1
          },
          "interface_protocol": 1,
          "interface_number": 1,
          "interface_alternate_setting": 0
        },
        "hotplug": "usb",
        "driver": "btusb",
        "driver_module": "btusb",
        "drivers": [
          "btusb"
        ],
        "driver_modules": [
          "btusb"
        ],
        "module_alias": "usb:v8087p07DCd0001dcE0dsc01dp01icE0isc01ip01in01"
      },
      {
        "index": 32,
        "attached_to": 34,
        "class_list": [
          "usb",
          "bluetooth"
        ],
        "bus_type": {
          "hex": "0086",
          "name": "USB",
          "value": 134
        },
        "slot": {
          "bus": 0,
          "number": 0
        },
        "base_class": {
          "hex": "0115",
          "name": "Bluetooth Device",
          "value": 277
        },
        "vendor": {
          "hex": "8087",
          "value": 32903
        },
        "device": {
          "hex": "07dc",
          "value": 2012
        },
        "revision": {
          "hex": "0000",
          "name": "0.01",
          "value": 0
        },
        "model": "Bluetooth Device",
        "sysfs_id": "/devices/pci0000:00/0000:00:14.0/usb2/2-7/2-7:1.0",
        "sysfs_bus_id": "2-7:1.0",
        "resources": [
          {
            "type": "baud",
            "speed": 12000000,
            "bits": 0,
            "stop_bits": 0,
            "parity": 0,
            "handshake": 0
          }
        ],
        "detail": {
          "device_class": {
            "hex": "00e0",
            "name": "wireless",
            "value": 224
          },
          "device_subclass": {
            "hex": "0001",
            "name": "audio",
            "value": 1
          },
          "device_protocol": 1,
          "interface_class": {
            "hex": "00e0",
            "name": "wireless",
            "value": 224
          },
          "interface_subclass": {
            "hex": "0001",
            "name": "audio",
            "value": 1
          },
          "interface_protocol": 1,
          "interface_number": 0,
          "interface_alternate_setting": 0
        },
        "hotplug": "usb",
        "driver": "btusb",
        "driver_module": "btusb",
        "drivers": [
          "btusb"
        ],
        "driver_modules": [
          "btusb"
        ],
        "module_alias": "usb:v8087p07DCd0001dcE0dsc01dp01icE0isc01ip01in00"
      }
    ],
    "bridge": [
      {
        "index": 10,
        "attached_to": 0,
        "class_list": [
          "pci",
          "bridge"
        ],
        "bus_type": {
          "hex": "0004",
          "name": "PCI",
          "value": 4
        },
        "slot": {
          "bus": 0,
          "number": 28
        },
        "base_class": {
          "hex": "0006",
          "name": "Bridge",
          "value": 6
        },
        "sub_class": {
          "hex": "0004",
          "name": "PCI bridge",
          "value": 4
        },
        "pci_interface": {
          "hex": "0000",
          "name": "Normal decode",
          "value": 0
        },
        "vendor": {
          "hex": "8086",
          "name": "Intel Corporation",
          "value": 32902
        },
        "sub_vendor": {
          "hex": "17aa",
          "value": 6058
        },
        "device": {
          "hex": "9c90",
          "value": 40080
        },
        "sub_device": {
          "hex": "3987",
          "value": 14727
        },
        "revision": {
          "hex": "00e3",
          "value": 227
        },
        "model": "Intel PCI bridge",
        "sysfs_id": "/devices/pci0000:00/0000:00:1c.0",
        "sysfs_bus_id": "0000:00:1c.0",
        "resources": [
          {
            "type": "irq",
            "base": 40,
            "triggered": 0,
            "enabled": true
          }
        ],
        "detail": {
          "function": 0,
          "command": 1031,
          "header_type": 1,
          "secondary_bus": 1,
          "irq": 40,
          "prog_if": 0
        },
        "driver": "pcieport",
        "driver_module": "pcieportdrv",
        "drivers": [
          "pcieport"
        ],
        "driver_modules": [
          "pcieportdrv"
        ],
        "module_alias": "pci:v00008086d00009C90sv000017AAsd00003987bc06sc04i00"
      },
      {
        "index": 11,
        "attached_to": 0,
        "class_list": [
          "pci",
          "bridge"
        ],
        "bus_type": {
          "hex": "0004",
          "name": "PCI",
          "value": 4
        },
        "slot": {
          "bus": 0,
          "number": 31
        },
        "base_class": {
          "hex": "0006",
          "name": "Bridge",
          "value": 6
        },
        "sub_class": {
          "hex": "0001",
          "name": "ISA bridge",
          "value": 1
        },
        "vendor": {
          "hex": "8086",
          "name": "Intel Corporation",
          "value": 32902
        },
        "sub_vendor": {
          "hex": "17aa",
          "value": 6058
        },
        "device": {
          "hex": "9cc3",
          "value": 40131
        },
        "sub_device": {
          "hex": "3987",
          "value": 14727
        },
        "revision": {
          "hex": "0003",
          "value": 3
        },
        "model": "Intel ISA bridge",
        "sysfs_id": "/devices/pci0000:00/0000:00:1f.0",
        "sysfs_bus_id": "0000:00:1f.0",
        "detail": {
          "function": 0,
          "command": 7,
          "header_type": 0,
          "secondary_bus": 0,
          "irq": 0,
          "prog_if": 0
        },
        "driver": "lpc_ich",
        "driver_module": "lpc_ich",
        "drivers": [
          "lpc_ich"
        ],
        "driver_modules": [
          "lpc_ich"
        ],
        "module_alias": "pci:v00008086d00009CC3sv000017AAsd00003987bc06sc01i00"
      },
      {
        "index": 15,
        "attached_to": 0,
        "class_list": [
          "pci",
          "bridge"
        ],
        "bus_type": {
          "hex": "0004",
          "name": "PCI",
          "value": 4
        },
        "slot": {
          "bus": 0,
          "number": 28
        },
        "base_class": {
          "hex": "0006",
          "name": "Bridge",
          "value": 6
        },
        "sub_class": {
          "hex": "0004",
          "name": "PCI bridge",
          "value": 4
        },
        "pci_interface": {
          "hex": "0000",
          "name": "Normal decode",
          "value": 0
        },
        "vendor": {
          "hex": "8086",
          "name": "Intel Corporation",
          "value": 32902
        },
        "sub_vendor": {
          "hex": "17aa",
          "value": 6058
        },
        "device": {
          "hex": "9c96",
          "value": 40086
        },
        "sub_device": {
          "hex": "3987",
          "value": 14727
        },
        "revision": {
          "hex": "00e3",
          "value": 227
        },
        "model": "Intel PCI bridge",
        "sysfs_id": "/devices/pci0000:00/0000:00:1c.3",
        "sysfs_bus_id": "0000:00:1c.3",
        "resources": [
          {
            "type": "irq",
            "base": 42,
            "triggered": 0,
            "enabled": true
          }
        ],
        "detail": {
          "function": 3,
          "command": 1031,
          "header_type": 1,
          "secondary_bus": 3,
          "irq": 42,
          "prog_if": 0
        },
        "driver": "pcieport",
        "driver_module": "pcieportdrv",
        "drivers": [
          "pcieport"
        ],
        "driver_modules": [
          "pcieportdrv"
        ],
        "module_alias": "pci:v00008086d00009C96sv000017AAsd00003987bc06sc04i00"
      },
      {
        "index": 17,
        "attached_to": 0,
        "class_list": [
          "pci",
          "bridge"
        ],
        "bus_type": {
          "hex": "0004",
          "name": "PCI",
          "value": 4
        },
        "slot": {
          "bus": 0,
          "number": 0
        },
        "base_class": {
          "hex": "0006",
          "name": "Bridge",
          "value": 6
        },
        "sub_class": {
          "hex": "0000",
          "name": "Host bridge",
          "value": 0
        },
        "vendor": {
          "hex": "8086",
          "name": "Intel Corporation",
          "value": 32902
        },
        "sub_vendor": {
          "hex": "17aa",
          "value": 6058
        },
        "device": {
          "hex": "1604",
          "value": 5636
        },
        "sub_device": {
          "hex": "3987",
          "value": 14727
        },
        "revision": {
          "hex": "0009",
          "value": 9
        },
        "model": "Intel Host bridge",
        "sysfs_id": "/devices/pci0000:00/0000:00:00.0",
        "sysfs_bus_id": "0000:00:00.0",
        "detail": {
          "function": 0,
          "command": 6,
          "header_type": 0,
          "secondary_bus": 0,
          "irq": 0,
          "prog_if": 0
        },
        "driver": "bdw_uncore",
        "driver_module": "intel_uncore",
        "drivers": [
          "bdw_uncore"
        ],
        "driver_modules": [
          "intel_uncore"
        ],
        "module_alias": "pci:v00008086d00001604sv000017AAsd00003987bc06sc00i00"
      },
      {
        "index": 22,
        "attached_to": 0,
        "class_list": [
          "pci",
          "bridge"
        ],
        "bus_type": {
          "hex": "0004",
          "name": "PCI",
          "value": 4
        },
        "slot": {
          "bus": 0,
          "number": 28
        },
        "base_class": {
          "hex": "0006",
          "name": "Bridge",
          "value": 6
        },
        "sub_class": {
          "hex": "0004",
          "name": "PCI bridge",
          "value": 4
        },
        "pci_interface": {
          "hex": "0000",
          "name": "Normal decode",
          "value": 0
        },
        "vendor": {
          "hex": "8086",
          "name": "Intel Corporation",
          "value": 32902
        },
        "sub_vendor": {
          "hex": "17aa",
          "value": 6058
        },
        "device": {
          "hex": "9c94",
          "value": 40084
        },
        "sub_device": {
          "hex": "3987",
          "value": 14727
        },
        "revision": {
          "hex": "00e3",
          "value": 227
        },
        "model": "Intel PCI bridge",
        "sysfs_id": "/devices/pci0000:00/0000:00:1c.2",
        "sysfs_bus_id": "0000:00:1c.2",
        "resources": [
          {
            "type": "irq",
            "base": 41,
            "triggered": 0,
            "enabled": true
          }
        ],
        "detail": {
          "function": 2,
          "command": 1031,
          "header_type": 1,
          "secondary_bus": 2,
          "irq": 41,
          "prog_if": 0
        },
        "driver": "pcieport",
        "driver_module": "pcieportdrv",
        "drivers": [
          "pcieport"
        ],
        "driver_modules": [
          "pcieportdrv"
        ],
        "module_alias": "pci:v00008086d00009C94sv000017AAsd00003987bc06sc04i00"
      }
    ],
    "camera": [
      {
        "index": 29,
        "attached_to": 34,
        "class_list": [
          "camera",
          "usb"
        ],
        "bus_type": {
          "hex": "0086",
          "name": "USB",
          "value": 134
        },
        "slot": {
          "bus": 0,
          "number": 0
        },
        "base_class": {
          "hex": "010f",
          "name": "Camera",
          "value": 271
        },
        "vendor": {
          "hex": "0c45",
          "name": "J5PF421DT",
          "value": 3141
        },
        "device": {
          "hex": "6513",
          "name": "Lenovo EasyCamera",
          "value": 25875
        },
        "revision": {
          "hex": "0000",
          "name": "0.12",
          "value": 0
        },
        "model": "J5PF421DT Lenovo EasyCamera",
        "sysfs_id": "/devices/pci0000:00/0000:00:14.0/usb2/2-6/2-6:1.0",
        "sysfs_bus_id": "2-6:1.0",
        "resources": [
          {
            "type": "baud",
            "speed": 480000000,
            "bits": 0,
            "stop_bits": 0,
            "parity": 0,
            "handshake": 0
          }
        ],
        "detail": {
          "device_class": {
            "hex": "00ef",
            "name": "miscellaneous",
            "value": 239
          },
          "device_subclass": {
            "hex": "0002",
            "name": "comm",
            "value": 2
          },
          "device_protocol": 1,
          "interface_class": {
            "hex": "000e",
            "name": "video",
            "value": 14
          },
          "interface_subclass": {
            "hex": "0001",
            "name": "audio",
            "value": 1
          },
          "interface_protocol": 0,
          "interface_number": 0,
          "interface_alternate_setting": 0,
          "interface_association": {
            "function_class": {
              "hex": "000e",
              "name": "video",
              "value": 14
            },
            "function_subclass": {
              "hex": "0003",
              "name": "hid",
              "value": 3
            },
            "function_protocol": 0,
            "interface_count": 2,
            "first_interface": 0
          }
        },
        "hotplug": "usb",
        "driver": "uvcvideo",
        "driver_module": "uvcvideo",
        "drivers": [
          "uvcvideo"
        ],
        "driver_modules": [
          "uvcvideo"
        ],
        "module_alias": "usb:v0C45p6513d0012dcEFdsc02dp01ic0Eisc01ip00in00"
      },
      {
        "index": 35,
        "attached_to": 34,
        "class_list": [
          "camera",
          "usb"
        ],
        "bus_type": {
          "hex": "0086",
          "name": "USB",
          "value": 134
        },
        "slot": {
          "bus": 0,
          "number": 0
        },
        "base_class": {
          "hex": "010f",
          "name": "Camera",
          "value": 271
        },
        "vendor": {
          "hex": "0c45",
          "name": "J5PF421DT",
          "value": 3141
        },
        "device": {
          "hex": "6513",
          "name": "Lenovo EasyCamera",
          "value": 25875
        },
        "revision": {
          "hex": "0000",
          "name": "0.12",
          "value": 0
        },
        "model": "J5PF421DT Lenovo EasyCamera",
        "sysfs_id": "/devices/pci0000:00/0000:00:14.0/usb2/2-6/2-6:1.1",
        "sysfs_bus_id": "2-6:1.1",
        "resources": [
          {
            "type": "baud",
            "speed": 480000000,
            "bits": 0,
            "stop_bits": 0,
            "parity": 0,
            "handshake": 0
          }
        ],
        "detail": {
          "device_class": {
            "hex": "00ef",
            "name": "miscellaneous",
            "value": 239
          },
          "device_subclass": {
            "hex": "0002",
            "name": "comm",
            "value": 2
          },
          "device_protocol": 1,
          "interface_class": {
            "hex": "000e",
            "name": "video",
            "value": 14
          },
          "interface_subclass": {
            "hex": "0002",
            "name": "comm",
            "value": 2
          },
          "interface_protocol": 0,
          "interface_number": 1,
          "interface_alternate_setting": 0,
          "interface_association": {
            "function_class": {
              "hex": "000e",
              "name": "video",
              "value": 14
            },
            "function_subclass": {
              "hex": "0003",
              "name": "hid",
              "value": 3
            },
            "function_protocol": 0,
            "interface_count": 2,
            "first_interface": 0
          }
        },
        "hotplug": "usb",
        "driver": "uvcvideo",
        "driver_module": "uvcvideo",
        "drivers": [
          "uvcvideo"
        ],
        "driver_modules": [
          "uvcvideo"
        ],
        "module_alias": "usb:v0C45p6513d0012dcEFdsc02dp01ic0Eisc02ip00in01"
      }
    ],
    "cdrom": [
      {
        "index": 24,
        "attached_to": 9,
        "class_list": [
          "cdrom",
          "scsi",
          "block_device"
        ],
        "bus_type": {
          "hex": "0084",
          "name": "SCSI",
          "value": 132
        },
        "slot": {
          "bus": 1,
          "number": 0
        },
        "base_class": {
          "hex": "0106",
          "name": "Mass Storage Device",
          "value": 262
        },
        "sub_class": {
          "hex": "0002",
          "name": "CD-ROM",
          "value": 2
        },
        "pci_interface": {
          "hex": "0003",
          "name": "DVD",
          "value": 3
        },
        "vendor": {
          "hex": "0000",
          "name": "PLDS",
          "value": 0
        },
        "device": {
          "hex": "0000",
          "name": "DVD-RW DA8A6SH",
          "value": 0
        },
        "revision": {
          "hex": "0000",
          "name": "GL61",
          "value": 0
        },
        "model": "PLDS DVD-RW DA8A6SH",
        "sysfs_id": "/class/block/sr0",
        "sysfs_bus_id": "1:0:0:0",
        "sysfs_device_link": "/devices/pci0000:00/0000:00:1f.2/ata2/host1/target1:0:0/1:0:0:0",
        "unix_device_name": "/dev/sr0",
        "unix_device_number": {
          "type": 98,
          "major": 11,
          "minor": 0,
          "range": 1
        },
        "unix_device_names": [
          "/dev/cdrom",
          "/dev/disk/by-id/ata-PLDS_DVD-RW_DA8A6SH_DX0F86404L1CB540CWS5",
          "/dev/disk/by-path/pci-0000:00:1f.2-ata-2",
          "/dev/disk/by-path/pci-0000:00:1f.2-ata-2.0",
          "/dev/sr0"
        ],
        "unix_device_name2": "/dev/sg1",
        "unix_device_number2": {
          "type": 99,
          "major": 21,
          "minor": 1,
          "range": 1
        },
        "driver": "ahci",
        "driver_module": "ahci",
        "drivers": [
          "ahci",
          "sr"
        ],
        "driver_modules": [
          "ahci",
          "sr_mod"
        ]
      }
    ],
    "cpu": [
      {
        "architecture": "x86_64",
        "vendor_name": "GenuineIntel",
        "family": 6,
        "model": 61,
        "stepping": 4,
        "features": [
          "fpu",
          "vme",
          "de",
          "pse",
          "tsc",
          "msr",
          "pae",
          "mce",
          "cx8",
          "apic",
          "sep",
          "mtrr",
          "pge",
          "mca",
          "cmov",
          "pat",
          "pse36",
          "clflush",
          "dts",
          "acpi",
          "mmx",
          "fxsr",
          "sse",
          "sse2",
          "ss",
          "ht",
          "tm",
          "pbe",
          "syscall",
          "nx",
          "pdpe1gb",
          "rdtscp",
          "lm",
          "constant_tsc",
          "arch_perfmon",
          "pebs",
          "bts",
          "rep_good",
          "nopl",
          "xtopology",
          "nonstop_tsc",
          "cpuid",
          "aperfmperf",
          "pni",
          "pclmulqdq",
          "dtes64",
          "monitor",
          "ds_cpl",
          "est",
          "tm2",
          "ssse3",
          "sdbg",
          "fma",
          "cx16",
          "xtpr",
          "pdcm",
          "pcid",
          "sse4_1",
          "sse4_2",
          "x2apic",
          "movbe",
          "popcnt",
          "aes",
          "xsave",
          "avx",
          "f16c",
          "rdrand",
          "lahf_lm",
          "abm",
          "3dnowprefetch",
          "cpuid_fault",
          "epb",
          "pti",
          "fsgsbase",
          "tsc_adjust",
          "bmi1",
          "avx2",
          "smep",
          "bmi2",
          "erms",
          "invpcid",
          "rdseed",
          "adx",
          "smap",
          "intel_pt",
          "xsaveopt",
          "dtherm",
          "ida",
          "arat",
          "pln",
          "pts"
        ],
        "bugs": [
          "cpu_meltdown",
          "spectre_v1",
          "spectre_v2",
          "spec_store_bypass",
          "l1tf",
          "mds",
          "swapgs",
          "itlb_multihit",
          "srbds",
          "mmio_unknown"
        ],
        "bogo": 4390.11,
        "cache": 3072,
        "units": 16,
        "physical_id": 0,
        "siblings": 4,
        "cores": 2,
        "fpu": true,
        "fpu_exception": true,
        "cpuid_level": 20,
        "write_protect": false,
        "clflush_size": 64,
        "cache_alignment": 64,
        "address_sizes": {
          "physical": "0x27",
          "virtual": "0x30"
        }
      }
    ],
    "disk": [
      {
        "index": 25,
        "attached_to": 9,
        "class_list": [
          "disk",
          "ide",
          "block_device"
        ],
        "bus_type": {
          "hex": "0085",
          "name": "IDE",
          "value": 133
        },
        "slot": {
          "bus": 0,
          "number": 0
        },
        "base_class": {
          "hex": "0106",
          "name": "Mass Storage Device",
          "value": 262
        },
        "sub_class": {
          "hex": "0000",
          "name": "Disk",
          "value": 0
        },
        "vendor": {
          "hex": "0000",
          "name": "WDC",
          "value": 0
        },
        "device": {
          "hex": "0000",
          "name": "WD10JPCX-24U",
          "value": 0
        },
        "revision": {
          "hex": "0000",
          "name": "1A01",
          "value": 0
        },
        "serial": "WD-WXH1EC4H1NSC",
        "model": "WDC WD10JPCX-24U",
        "sysfs_id": "/class/block/sda",
        "sysfs_bus_id": "0:0:0:0",
        "sysfs_device_link": "/devices/pci0000:00/0000:00:1f.2/ata1/host0/target0:0:0/0:0:0:0",
        "unix_device_name": "/dev/sda",
        "unix_device_number": {
          "type": 98,
          "major": 8,
          "minor": 0,
          "range": 16
        },
        "unix_device_names": [
          "/dev/disk/by-id/ata-WDC_WD10JPCX-24UE4T0_WD-WXH1EC4H1NSC",
          "/dev/disk/by-id/wwn-0x50014ee65b035dae",
          "/dev/disk/by-path/pci-0000:00:1f.2-ata-1",
          "/dev/disk/by-path/pci-0000:00:1f.2-ata-1.0",
          "/dev/sda"
        ],
        "rom_id": "0x80",
        "resources": [
          {
            "type": "disk_geo",
            "cylinders": 121601,
            "heads": 255,
            "sectors": 63,
            "size": "0x0",
            "geo_type": "logical"
          },
          {
            "type": "size",
            "unit": "sectors",
            "value_1": 1953525168,
            "value_2": 512
          }
        ],
        "driver": "ahci",
        "driver_module": "ahci",
        "drivers": [
          "ahci",
          "sd"
        ],
        "driver_modules": [
          "ahci",
          "sd_mod"
        ]
      }
    ],
    "graphics_card": [
      {
        "index": 20,
        "attached_to": 0,
        "class_list": [
          "graphics_card",
          "pci"
        ],
        "bus_type": {
          "hex": "0004",
          "name": "PCI",
          "value": 4
        },
        "slot": {
          "bus": 0,
          "number": 2
        },
        "base_class": {
          "hex": "0003",
          "name": "Display controller",
          "value": 3
        },
        "sub_class": {
          "hex": "0000",
          "name": "VGA compatible controller",
          "value": 0
        },
        "pci_interface": {
          "hex": "0000",
          "name": "VGA",
          "value": 0
        },
        "vendor": {
          "hex": "8086",
          "name": "Intel Corporation",
          "value": 32902
        },
        "sub_vendor": {
          "hex": "17aa",
          "value": 6058
        },
        "device": {
          "hex": "1616",
          "value": 5654
        },
        "sub_device": {
          "hex": "3987",
          "value": 14727
        },
        "revision": {
          "hex": "0009",
          "value": 9
        },
        "model": "Intel VGA compatible controller",
        "sysfs_id": "/devices/pci0000:00/0000:00:02.0",
        "sysfs_bus_id": "0000:00:02.0",
        "resources": [
          {
            "type": "io",
            "base": 16384,
            "range": 64,
            "enabled": true,
            "access": "read_write"
          },
          {
            "type": "irq",
            "base": 53,
            "triggered": 0,
            "enabled": true
          },
          {
            "type": "mem",
            "base": 2952790016,
            "range": 268435456,
            "enabled": true,
            "access": "read_only",
            "prefetch": "no"
          },
          {
            "type": "mem",
            "base": 3221225472,
            "range": 16777216,
            "enabled": true,
            "access": "read_write",
            "prefetch": "no"
          },
          {
            "type": "mem",
            "base": 786432,
            "range": 131072,
            "enabled": false,
            "access": "read_write",
            "prefetch": "no"
          }
        ],
        "detail": {
          "function": 0,
          "command": 1031,
          "header_type": 0,
          "secondary_bus": 0,
          "irq": 53,
          "prog_if": 0
        },
        "driver": "i915",
        "driver_module": "i915",
        "drivers": [
          "i915"
        ],
        "driver_modules": [
          "i915"
        ],
        "module_alias": "pci:v00008086d00001616sv000017AAsd00003987bc03sc00i00"
      }
    ],
    "hub": [
      {
        "index": 28,
        "attached_to": 21,
        "class_list": [
          "usb",
          "hub"
        ],
        "bus_type": {
          "hex": "0086",
          "name": "USB",
          "value": 134
        },
        "slot": {
          "bus": 0,
          "number": 0
        },
        "base_class": {
          "hex": "010a",
          "name": "Hub",
          "value": 266
        },
        "vendor": {
          "hex": "1d6b",
          "name": "Linux 6.14.10 xhci-hcd",
          "value": 7531
        },
        "device": {
          "hex": "0003",
          "name": "xHCI Host Controller",
          "value": 3
        },
        "revision": {
          "hex": "0000",
          "name": "6.14",
          "value": 0
        },
        "serial": "0000:00:14.0",
        "model": "Linux 6.14.10 xhci-hcd xHCI Host Controller",
        "sysfs_id": "/devices/pci0000:00/0000:00:14.0/usb3/3-0:1.0",
        "sysfs_bus_id": "3-0:1.0",
        "detail": {
          "device_class": {
            "hex": "0009",
            "name": "hub",
            "value": 9
          },
          "device_subclass": {
            "hex": "0000",
            "name": "per_interface",
            "value": 0
          },
          "device_protocol": 3,
          "interface_class": {
            "hex": "0009",
            "name": "hub",
            "value": 9
          },
          "interface_subclass": {
            "hex": "0000",
            "name": "per_interface",
            "value": 0
          },
          "interface_protocol": 0,
          "interface_number": 0,
          "interface_alternate_setting": 0
        },
        "hotplug": "usb",
        "driver": "hub",
        "driver_module": "usbcore",
        "drivers": [
          "hub"
        ],
        "driver_modules": [
          "usbcore"
        ],
        "module_alias": "usb:v1D6Bp0003d0614dc09dsc00dp03ic09isc00ip00in00"
      },
      {
        "index": 30,
        "attached_to": 19,
        "class_list": [
          "usb",
          "hub"
        ],
        "bus_type": {
          "hex": "0086",
          "name": "USB",
          "value": 134
        },
        "slot": {
          "bus": 0,
          "number": 0
        },
        "base_class": {
          "hex": "010a",
          "name": "Hub",
          "value": 266
        },
        "vendor": {
          "hex": "1d6b",
          "name": "Linux 6.14.10 ehci_hcd",
          "value": 7531
        },
        "device": {
          "hex": "0002",
          "name": "EHCI Host Controller",
          "value": 2
        },
        "revision": {
          "hex": "0000",
          "name": "6.14",
          "value": 0
        },
        "serial": "0000:00:1d.0",
        "model": "Linux 6.14.10 ehci_hcd EHCI Host Controller",
        "sysfs_id": "/devices/pci0000:00/0000:00:1d.0/usb1/1-0:1.0",
        "sysfs_bus_id": "1-0:1.0",
        "resources": [
          {
            "type": "baud",
            "speed": 480000000,
            "bits": 0,
            "stop_bits": 0,
            "parity": 0,
            "handshake": 0
          }
        ],
        "detail": {
          "device_class": {
            "hex": "0009",
            "name": "hub",
            "value": 9
          },
          "device_subclass": {
            "hex": "0000",
            "name": "per_interface",
            "value": 0
          },
          "device_protocol": 0,
          "interface_class": {
            "hex": "0009",
            "name": "hub",
            "value": 9
          },
          "interface_subclass": {
            "hex": "0000",
            "name": "per_interface",
            "value": 0
          },
          "interface_protocol": 0,
          "interface_number": 0,
          "interface_alternate_setting": 0
        },
        "hotplug": "usb",
        "driver": "hub",
        "driver_module": "usbcore",
        "drivers": [
          "hub"
        ],
        "driver_modules": [
          "usbcore"
        ],
        "module_alias": "usb:v1D6Bp0002d0614dc09dsc00dp00ic09isc00ip00in00"
      },
      {
        "index": 33,
        "attached_to": 30,
        "class_list": [
          "usb",
          "hub"
        ],
        "bus_type": {
          "hex": "0086",
          "name": "USB",
          "value": 134
        },
        "slot": {
          "bus": 0,
          "number": 0
        },
        "base_class": {
          "hex": "010a",
          "name": "Hub",
          "value": 266
        },
        "vendor": {
          "hex": "8087",
          "value": 32903
        },
        "device": {
          "hex": "8001",
          "value": 32769
        },
        "revision": {
          "hex": "0000",
          "name": "0.03",
          "value": 0
        },
        "model": "Hub",
        "sysfs_id": "/devices/pci0000:00/0000:00:1d.0/usb1/1-1/1-1:1.0",
        "sysfs_bus_id": "1-1:1.0",
        "resources": [
          {
            "type": "baud",
            "speed": 480000000,
            "bits": 0,
            "stop_bits": 0,
            "parity": 0,
            "handshake": 0
          }
        ],
        "detail": {
          "device_class": {
            "hex": "0009",
            "name": "hub",
            "value": 9
          },
          "device_subclass": {
            "hex": "0000",
            "name": "per_interface",
            "value": 0
          },
          "device_protocol": 1,
          "interface_class": {
            "hex": "0009",
            "name": "hub",
            "value": 9
          },
          "interface_subclass": {
            "hex": "0000",
            "name": "per_interface",
            "value": 0
          },
          "interface_protocol": 0,
          "interface_number": 0,
          "interface_alternate_setting": 0
        },
        "hotplug": "usb",
        "driver": "hub",
        "driver_module": "usbcore",
        "drivers": [
          "hub"
        ],
        "driver_modules": [
          "usbcore"
        ],
        "module_alias": "usb:v8087p8001d0003dc09dsc00dp01ic09isc00ip00in00"
      },
      {
        "index": 34,
        "attached_to": 21,
        "class_list": [
          "usb",
          "hub"
        ],
        "bus_type": {
          "hex": "0086",
          "name": "USB",
          "value": 134
        },
        "slot": {
          "bus": 0,
          "number": 0
        },
        "base_class": {
          "hex": "010a",
          "name": "Hub",
          "value": 266
        },
        "vendor": {
          "hex": "1d6b",
          "name": "Linux 6.14.10 xhci-hcd",
          "value": 7531
        },
        "device": {
          "hex": "0002",
          "name": "xHCI Host Controller",
          "value": 2
        },
        "revision": {
          "hex": "0000",
          "name": "6.14",
          "value": 0
        },
        "serial": "0000:00:14.0",
        "model": "Linux 6.14.10 xhci-hcd xHCI Host Controller",
        "sysfs_id": "/devices/pci0000:00/0000:00:14.0/usb2/2-0:1.0",
        "sysfs_bus_id": "2-0:1.0",
        "resources": [
          {
            "type": "baud",
            "speed": 480000000,
            "bits": 0,
            "stop_bits": 0,
            "parity": 0,
            "handshake": 0
          }
        ],
        "detail": {
          "device_class": {
            "hex": "0009",
            "name": "hub",
            "value": 9
          },
          "device_subclass": {
            "hex": "0000",
            "name": "per_interface",
            "value": 0
          },
          "device_protocol": 1,
          "interface_class": {
            "hex": "0009",
            "name": "hub",
            "value": 9
          },
          "interface_subclass": {
            "hex": "0000",
            "name": "per_interface",
            "value": 0
          },
          "interface_protocol": 0,
          "interface_number": 0,
          "interface_alternate_setting": 0
        },
        "hotplug": "usb",
        "driver": "hub",
        "driver_module": "usbcore",
        "drivers": [
          "hub"
        ],
        "driver_modules": [
          "usbcore"
        ],
        "module_alias": "usb:v1D6Bp0002d0614dc09dsc00dp01ic09isc00ip00in00"
      }
    ],
    "memory": [
      {
        "index": 7,
        "attached_to": 0,
        "class_list": [
          "memory"
        ],
        "base_class": {
          "hex": "0101",
          "name": "Internally Used Class",
          "value": 257
        },
        "sub_class": {
          "hex": "0002",
          "name": "Main Memory",
          "value": 2
        },
        "model": "Main Memory",
        "resources": [
          {
            "type": "mem",
            "base": 0,
            "range": 8247021568,
            "enabled": true,
            "access": "read_write",
            "prefetch": "unknown"
          },
          {
            "type": "phys_mem",
            "range": 8053063680
          }
        ]
      }
    ],
    "monitor": [
      {
        "index": 23,
        "attached_to": 20,
        "class_list": [
          "monitor"
        ],
        "base_class": {
          "hex": "0100",
          "name": "Monitor",
          "value": 256
        },
        "sub_class": {
          "hex": "0002",
          "name": "LCD Monitor",
          "value": 2
        },
        "vendor": {
          "hex": "0dae",
          "name": "N173FGE-E13",
          "value": 3502
        },
        "device": {
          "hex": "1721",
          "value": 5921
        },
        "serial": "0",
        "model": "N173FGE-E13 LCD Monitor",
        "resources": [
          {
            "type": "monitor",
            "width": 1600,
            "height": 900,
            "vertical_frequency": 60,
            "interlaced": false
          },
          {
            "type": "size",
            "unit": "mm",
            "value_1": 382,
            "value_2": 214
          }
        ],
        "detail": {
          "manufacture_year": 2015,
          "manufacture_week": 3,
          "vertical_sync": {
            "min": 0,
            "max": 0
          },
          "horizontal_sync": {
            "min": 0,
            "max": 0
          },
          "horizontal_sync_timings": {
            "disp": 1600,
            "sync_start": 1648,
            "sync_end": 1680,
            "total": 1940
          },
          "vertical_sync_timings": {
            "disp": 900,
            "sync_start": 903,
            "sync_end": 908,
            "total": 926
          },
          "clock": 107800,
          "width": 1600,
          "height": 900,
          "width_millimetres": 382,
          "height_millimetres": 214,
          "horizontal_flag": 45,
          "vertical_flag": 45,
          "vendor": "N173FGE-E13",
          "name": ""
        }
      }
    ],
    "mouse": [
      {
        "index": 39,
        "attached_to": 0,
        "bus_type": {
          "hex": "0080",
          "name": "ps2",
          "value": 128
        },
        "base_class": {
          "hex": "0118",
          "name": "touchpad",
          "value": 280
        },
        "sub_class": {
          "hex": "0000",
          "name": "ps2",
          "value": 0
        },
        "vendor": {
          "hex": "0002",
          "value": 2
        },
        "device": {
          "hex": "0007",
          "value": 7
        },
        "sysfs_id": "/devices/platform/i8042/serio1/input/input5",
        "unix_device_names": [
          "/dev/input/event8",
          "/dev/input/ + handler"
        ]
      }
    ],
    "network_controller": [
      {
        "index": 8,
        "attached_to": 15,
        "class_list": [
          "network_controller",
          "pci"
        ],
        "bus_type": {
          "hex": "0004",
          "name": "PCI",
          "value": 4
        },
        "slot": {
          "bus": 3,
          "number": 0
        },
        "base_class": {
          "hex": "0002",
          "name": "Network controller",
          "value": 2
        },
        "sub_class": {
          "hex": "0080",
          "name": "Network controller",
          "value": 128
        },
        "vendor": {
          "hex": "8086",
          "name": "Intel Corporation",
          "value": 32902
        },
        "sub_vendor": {
          "hex": "8086",
          "name": "Intel Corporation",
          "value": 32902
        },
        "device": {
          "hex": "08b4",
          "value": 2228
        },
        "sub_device": {
          "hex": "8270",
          "value": 33392
        },
        "revision": {
          "hex": "0093",
          "value": 147
        },
        "model": "Intel Network controller",
        "sysfs_id": "/devices/pci0000:00/0000:00:1c.3/0000:03:00.0",
        "sysfs_bus_id": "0000:03:00.0",
        "resources": [
          {
            "type": "irq",
            "base": 19,
            "triggered": 0,
            "enabled": true
          },
          {
            "type": "mem",
            "base": 3238002688,
            "range": 8192,
            "enabled": true,
            "access": "read_write",
            "prefetch": "no"
          }
        ],
        "detail": {
          "function": 0,
          "command": 2,
          "header_type": 0,
          "secondary_bus": 0,
          "irq": 19,
          "prog_if": 0
        },
        "module_alias": "pci:v00008086d000008B4sv00008086sd00008270bc02sc80i00"
      },
      {
        "index": 12,
        "attached_to": 22,
        "class_list": [
          "network_controller",
          "pci"
        ],
        "bus_type": {
          "hex": "0004",
          "name": "PCI",
          "value": 4
        },
        "slot": {
          "bus": 2,
          "number": 0
        },
        "base_class": {
          "hex": "0002",
          "name": "Network controller",
          "value": 2
        },
        "sub_class": {
          "hex": "0000",
          "name": "Ethernet controller",
          "value": 0
        },
        "vendor": {
          "hex": "10ec",
          "value": 4332
        },
        "sub_vendor": {
          "hex": "17aa",
          "value": 6058
        },
        "device": {
          "hex": "8168",
          "value": 33128
        },
        "sub_device": {
          "hex": "3819",
          "value": 14361
        },
        "revision": {
          "hex": "0010",
          "value": 16
        },
        "model": "Ethernet controller",
        "sysfs_id": "/devices/pci0000:00/0000:00:1c.2/0000:02:00.0",
        "sysfs_bus_id": "0000:02:00.0",
        "unix_device_name": "enp2s0",
        "unix_device_names": [
          "enp2s0"
        ],
        "resources": [
          {
            "type": "hwaddr",
            "address": 54
          },
          {
            "type": "io",
            "base": 12288,
            "range": 256,
            "enabled": true,
            "access": "read_write"
          },
          {
            "type": "irq",
            "base": 18,
            "triggered": 0,
            "enabled": true
          },
          {
            "type": "mem",
            "base": 3239051264,
            "range": 16384,
            "enabled": true,
            "access": "read_write",
            "prefetch": "no"
          },
          {
            "type": "mem",
            "base": 3239067648,
            "range": 4096,
            "enabled": true,
            "access": "read_write",
            "prefetch": "no"
          },
          {
            "type": "phwaddr",
            "address": 54
          }
        ],
        "detail": {
          "function": 0,
          "command": 1031,
          "header_type": 0,
          "secondary_bus": 0,
          "irq": 18,
          "prog_if": 0
        },
        "driver": "r8169",
        "driver_module": "r8169",
        "drivers": [
          "r8169"
        ],
        "driver_modules": [
          "r8169"
        ],
        "module_alias": "pci:v000010ECd00008168sv000017AAsd00003819bc02sc00i00"
      },
      {
        "index": 31,
        "attached_to": 34,
        "class_list": [
          "network_controller",
          "usb"
        ],
        "bus_type": {
          "hex": "0086",
          "name": "USB",
          "value": 134
        },
        "slot": {
          "bus": 0,
          "number": 0
        },
        "base_class": {
          "hex": "0002",
          "name": "Network controller",
          "value": 2
        },
        "sub_class": {
          "hex": "0000",
          "name": "Ethernet controller",
          "value": 0
        },
        "vendor": {
          "hex": "0bda",
          "name": "Realtek",
          "value": 3034
        },
        "device": {
          "hex": "8153",
          "name": "USB 10/100/1000 LAN",
          "value": 33107
        },
        "revision": {
          "hex": "0000",
          "name": "30.00",
          "value": 0
        },
        "serial": "000001",
        "model": "Realtek USB 10/100/1000 LAN",
        "sysfs_id": "/devices/pci0000:00/0000:00:14.0/usb2/2-3/2-3:1.0",
        "sysfs_bus_id": "2-3:1.0",
        "unix_device_name": "enp0s20u3",
        "unix_device_names": [
          "enp0s20u3"
        ],
        "resources": [
          {
            "type": "baud",
            "speed": 480000000,
            "bits": 0,
            "stop_bits": 0,
            "parity": 0,
            "handshake": 0
          },
          {
            "type": "hwaddr",
            "address": 48
          },
          {
            "type": "phwaddr",
            "address": 48
          }
        ],
        "detail": {
          "device_class": {
            "hex": "0000",
            "name": "per_interface",
            "value": 0
          },
          "device_subclass": {
            "hex": "0000",
            "name": "per_interface",
            "value": 0
          },
          "device_protocol": 0,
          "interface_class": {
            "hex": "00ff",
            "name": "vendor_spec",
            "value": 255
          },
          "interface_subclass": {
            "hex": "00ff",
            "name": "vendor_spec",
            "value": 255
          },
          "interface_protocol": 0,
          "interface_number": 0,
          "interface_alternate_setting": 0
        },
        "hotplug": "usb",
        "driver": "r8152",
        "driver_module": "r8152",
        "drivers": [
          "r8152"
        ],
        "driver_modules": [
          "r8152"
        ],
        "module_alias": "usb:v0BDAp8153d3000dc00dsc00dp00icFFiscFFip00in00"
      }
    ],
    "network_interface": [
      {
        "index": 36,
        "attached_to": 12,
        "class_list": [
          "network_interface"
        ],
        "base_class": {
          "hex": "0107",
          "name": "Network Interface",
          "value": 263
        },
        "sub_class": {
          "hex": "0001",
          "name": "Ethernet",
          "value": 1
        },
        "model": "Ethernet network interface",
        "sysfs_id": "/class/net/enp2s0",
        "sysfs_device_link": "/devices/pci0000:00/0000:00:1c.2/0000:02:00.0",
        "unix_device_name": "enp2s0",
        "unix_device_names": [
          "enp2s0"
        ],
        "resources": [
          {
            "type": "hwaddr",
            "address": 54
          },
          {
            "type": "phwaddr",
            "address": 54
          }
        ],
        "driver": "r8169",
        "driver_module": "r8169",
        "drivers": [
          "r8169"
        ],
        "driver_modules": [
          "r8169"
        ]
      },
      {
        "index": 37,
        "attached_to": 31,
        "class_list": [
          "network_interface"
        ],
        "base_class": {
          "hex": "0107",
          "name": "Network Interface",
          "value": 263
        },
        "sub_class": {
          "hex": "0001",
          "name": "Ethernet",
          "value": 1
        },
        "model": "Ethernet network interface",
        "sysfs_id": "/class/net/enp0s20u3",
        "sysfs_device_link": "/devices/pci0000:00/0000:00:14.0/usb2/2-3/2-3:1.0",
        "unix_device_name": "enp0s20u3",
        "unix_device_names": [
          "enp0s20u3"
        ],
        "resources": [
          {
            "type": "hwaddr",
            "address": 48
          },
          {
            "type": "phwaddr",
            "address": 48
          }
        ],
        "driver": "r8152",
        "driver_module": "r8152",
        "drivers": [
          "r8152"
        ],
        "driver_modules": [
          "r8152"
        ]
      },
      {
        "index": 38,
        "attached_to": 0,
        "class_list": [
          "network_interface"
        ],
        "base_class": {
          "hex": "0107",
          "name": "Network Interface",
          "value": 263
        },
        "sub_class": {
          "hex": "0000",
          "name": "Loopback",
          "value": 0
        },
        "model": "Loopback network interface",
        "sysfs_id": "/class/net/lo",
        "unix_device_name": "lo",
        "unix_device_names": [
          "lo"
        ]
      }
    ],
    "pci": [
      {
        "index": 13,
        "attached_to": 0,
        "class_list": [
          "pci",
          "unknown"
        ],
        "bus_type": {
          "hex": "0004",
          "name": "PCI",
          "value": 4
        },
        "slot": {
          "bus": 0,
          "number": 22
        },
        "base_class": {
          "hex": "0007",
          "name": "Communication controller",
          "value": 7
        },
        "sub_class": {
          "hex": "0080",
          "name": "Communication controller",
          "value": 128
        },
        "vendor": {
          "hex": "8086",
          "name": "Intel Corporation",
          "value": 32902
        },
        "sub_vendor": {
          "hex": "17aa",
          "value": 6058
        },
        "device": {
          "hex": "9cba",
          "value": 40122
        },
        "sub_device": {
          "hex": "3987",
          "value": 14727
        },
        "revision": {
          "hex": "0003",
          "value": 3
        },
        "model": "Intel Communication controller",
        "sysfs_id": "/devices/pci0000:00/0000:00:16.0",
        "sysfs_bus_id": "0000:00:16.0",
        "resources": [
          {
            "type": "irq",
            "base": 49,
            "triggered": 0,
            "enabled": true
          },
          {
            "type": "mem",
            "base": 3240210432,
            "range": 32,
            "enabled": true,
            "access": "read_write",
            "prefetch": "no"
          }
        ],
        "detail": {
          "function": 0,
          "command": 1030,
          "header_type": 0,
          "secondary_bus": 0,
          "irq": 49,
          "prog_if": 0
        },
        "driver": "mei_me",
        "driver_module": "mei_me",
        "drivers": [
          "mei_me"
        ],
        "driver_modules": [
          "mei_me"
        ],
        "module_alias": "pci:v00008086d00009CBAsv000017AAsd00003987bc07sc80i00"
      },
      {
        "index": 16,
        "attached_to": 0,
        "class_list": [
          "pci",
          "unknown"
        ],
        "bus_type": {
          "hex": "0004",
          "name": "PCI",
          "value": 4
        },
        "slot": {
          "bus": 0,
          "number": 31
        },
        "base_class": {
          "hex": "000c",
          "name": "Serial bus controller",
          "value": 12
        },
        "sub_class": {
          "hex": "0005",
          "name": "SMBus",
          "value": 5
        },
        "vendor": {
          "hex": "8086",
          "name": "Intel Corporation",
          "value": 32902
        },
        "sub_vendor": {
          "hex": "17aa",
          "value": 6058
        },
        "device": {
          "hex": "9ca2",
          "value": 40098
        },
        "sub_device": {
          "hex": "3987",
          "value": 14727
        },
        "revision": {
          "hex": "0003",
          "value": 3
        },
        "model": "Intel SMBus",
        "sysfs_id": "/devices/pci0000:00/0000:00:1f.3",
        "sysfs_bus_id": "0000:00:1f.3",
        "resources": [
          {
            "type": "io",
            "base": 16448,
            "range": 32,
            "enabled": true,
            "access": "read_write"
          },
          {
            "type": "irq",
            "base": 18,
            "triggered": 0,
            "enabled": true
          },
          {
            "type": "mem",
            "base": 3240206336,
            "range": 256,
            "enabled": true,
            "access": "read_write",
            "prefetch": "no"
          }
        ],
        "detail": {
          "function": 3,
          "command": 3,
          "header_type": 0,
          "secondary_bus": 0,
          "irq": 18,
          "prog_if": 0
        },
        "driver": "i801_smbus",
        "driver_module": "i2c_i801",
        "drivers": [
          "i801_smbus"
        ],
        "driver_modules": [
          "i2c_i801"
        ],
        "module_alias": "pci:v00008086d00009CA2sv000017AAsd00003987bc0Csc05i00"
      }
    ],
    "sound": [
      {
        "index": 14,
        "attached_to": 0,
        "class_list": [
          "sound",
          "pci"
        ],
        "bus_type": {
          "hex": "0004",
          "name": "PCI",
          "value": 4
        },
        "slot": {
          "bus": 0,
          "number": 27
        },
        "base_class": {
          "hex": "0004",
          "name": "Multimedia controller",
          "value": 4
        },
        "sub_class": {
          "hex": "0003",
          "value": 3
        },
        "vendor": {
          "hex": "8086",
          "name": "Intel Corporation",
          "value": 32902
        },
        "sub_vendor": {
          "hex": "17aa",
          "value": 6058
        },
        "device": {
          "hex": "9ca0",
          "value": 40096
        },
        "sub_device": {
          "hex": "3987",
          "value": 14727
        },
        "revision": {
          "hex": "0003",
          "value": 3
        },
        "model": "Intel Multimedia controller",
        "sysfs_id": "/devices/pci0000:00/0000:00:1b.0",
        "sysfs_bus_id": "0000:00:1b.0",
        "resources": [
          {
            "type": "irq",
            "base": 51,
            "triggered": 0,
            "enabled": true
          },
          {
            "type": "mem",
            "base": 3240181760,
            "range": 16384,
            "enabled": true,
            "access": "read_write",
            "prefetch": "no"
          }
        ],
        "detail": {
          "function": 0,
          "command": 1030,
          "header_type": 0,
          "secondary_bus": 0,
          "irq": 51,
          "prog_if": 0
        },
        "driver": "snd_hda_intel",
        "driver_module": "snd_hda_intel",
        "drivers": [
          "snd_hda_intel"
        ],
        "driver_modules": [
          "snd_hda_intel"
        ],
        "module_alias": "pci:v00008086d00009CA0sv000017AAsd00003987bc04sc03i00"
      },
      {
        "index": 18,
        "attached_to": 0,
        "class_list": [
          "sound",
          "pci"
        ],
        "bus_type": {
          "hex": "0004",
          "name": "PCI",
          "value": 4
        },
        "slot": {
          "bus": 0,
          "number": 3
        },
        "base_class": {
          "hex": "0004",
          "name": "Multimedia controller",
          "value": 4
        },
        "sub_class": {
          "hex": "0003",
          "value": 3
        },
        "vendor": {
          "hex": "8086",
          "name": "Intel Corporation",
          "value": 32902
        },
        "sub_vendor": {
          "hex": "17aa",
          "value": 6058
        },
        "device": {
          "hex": "160c",
          "value": 5644
        },
        "sub_device": {
          "hex": "3987",
          "value": 14727
        },
        "revision": {
          "hex": "0009",
          "value": 9
        },
        "model": "Intel Multimedia controller",
        "sysfs_id": "/devices/pci0000:00/0000:00:03.0",
        "sysfs_bus_id": "0000:00:03.0",
        "resources": [
          {
            "type": "irq",
            "base": 52,
            "triggered": 0,
            "enabled": true
          },
          {
            "type": "mem",
            "base": 3240165376,
            "range": 16384,
            "enabled": true,
            "access": "read_write",
            "prefetch": "no"
          }
        ],
        "detail": {
          "function": 0,
          "command": 1030,
          "header_type": 0,
          "secondary_bus": 0,
          "irq": 52,
          "prog_if": 0
        },
        "driver": "snd_hda_intel",
        "driver_module": "snd_hda_intel",
        "drivers": [
          "snd_hda_intel"
        ],
        "driver_modules": [
          "snd_hda_intel"
        ],
        "module_alias": "pci:v00008086d0000160Csv000017AAsd00003987bc04sc03i00"
      }
    ],
    "storage_controller": [
      {
        "index": 9,
        "attached_to": 0,
        "class_list": [
          "storage_controller",
          "pci"
        ],
        "bus_type": {
          "hex": "0004",
          "name": "PCI",
          "value": 4
        },
        "slot": {
          "bus": 0,
          "number": 31
        },
        "base_class": {
          "hex": "0001",
          "name": "Mass storage controller",
          "value": 1
        },
        "sub_class": {
          "hex": "0006",
          "value": 6
        },
        "pci_interface": {
          "hex": "0001",
          "value": 1
        },
        "vendor": {
          "hex": "8086",
          "name": "Intel Corporation",
          "value": 32902
        },
        "sub_vendor": {
          "hex": "17aa",
          "value": 6058
        },
        "device": {
          "hex": "9c83",
          "value": 40067
        },
        "sub_device": {
          "hex": "3987",
          "value": 14727
        },
        "revision": {
          "hex": "0003",
          "value": 3
        },
        "model": "Intel Mass storage controller",
        "sysfs_id": "/devices/pci0000:00/0000:00:1f.2",
        "sysfs_bus_id": "0000:00:1f.2",
        "resources": [
          {
            "type": "io",
            "base": 16480,
            "range": 32,
            "enabled": true,
            "access": "read_write"
          },
          {
            "type": "io",
            "base": 16512,
            "range": 8,
            "enabled": true,
            "access": "read_write"
          },
          {
            "type": "io",
            "base": 16520,
            "range": 8,
            "enabled": true,
            "access": "read_write"
          },
          {
            "type": "io",
            "base": 16528,
            "range": 4,
            "enabled": true,
            "access": "read_write"
          },
          {
            "type": "io",
            "base": 16532,
            "range": 4,
            "enabled": true,
            "access": "read_write"
          },
          {
            "type": "irq",
            "base": 48,
            "triggered": 0,
            "enabled": true
          },
          {
            "type": "mem",
            "base": 3240198144,
            "range": 2048,
            "enabled": true,
            "access": "read_write",
            "prefetch": "no"
          }
        ],
        "detail": {
          "function": 2,
          "command": 1031,
          "header_type": 0,
          "secondary_bus": 0,
          "irq": 48,
          "prog_if": 1
        },
        "driver": "ahci",
        "driver_module": "ahci",
        "drivers": [
          "ahci"
        ],
        "driver_modules": [
          "ahci"
        ],
        "module_alias": "pci:v00008086d00009C83sv000017AAsd00003987bc01sc06i01"
      }
    ],
    "system": {
      "form_factor": "laptop"
    },
    "usb": [
      {
        "index": 26,
        "attached_to": 34,
        "class_list": [
          "usb",
          "unknown"
        ],
        "bus_type": {
          "hex": "0086",
          "name": "USB",
          "value": 134
        },
        "slot": {
          "bus": 0,
          "number": 0
        },
        "base_class": {
          "hex": "0000",
          "name": "Unclassified device",
          "value": 0
        },
        "sub_class": {
          "hex": "0000",
          "name": "Unclassified device",
          "value": 0
        },
        "vendor": {
          "hex": "0bda",
          "name": "Generic",
          "value": 3034
        },
        "device": {
          "hex": "0129",
          "name": "USB2.0-CRW",
          "value": 297
        },
        "revision": {
          "hex": "0000",
          "name": "39.60",
          "value": 0
        },
        "serial": "20100201396000000",
        "model": "Generic USB2.0-CRW",
        "sysfs_id": "/devices/pci0000:00/0000:00:14.0/usb2/2-4/2-4:1.0",
        "sysfs_bus_id": "2-4:1.0",
        "resources": [
          {
            "type": "baud",
            "speed": 480000000,
            "bits": 0,
            "stop_bits": 0,
            "parity": 0,
            "handshake": 0
          }
        ],
        "detail": {
          "device_class": {
            "hex": "00ff",
            "name": "vendor_spec",
            "value": 255
          },
          "device_subclass": {
            "hex": "00ff",
            "name": "vendor_spec",
            "value": 255
          },
          "device_protocol": 255,
          "interface_class": {
            "hex": "00ff",
            "name": "vendor_spec",
            "value": 255
          },
          "interface_subclass": {
            "hex": "0006",
            "name": "image",
            "value": 6
          },
          "interface_protocol": 80,
          "interface_number": 0,
          "interface_alternate_setting": 0
        },
        "hotplug": "usb",
        "driver": "rtsx_usb",
        "driver_module": "rtsx_usb",
        "drivers": [
          "rtsx_usb"
        ],
        "driver_modules": [
          "rtsx_usb"
        ],
        "module_alias": "usb:v0BDAp0129d3960dcFFdscFFdpFFicFFisc06ip50in00"
      }
    ],
    "usb_controller": [
      {
        "index": 19,
        "attached_to": 0,
        "class_list": [
          "usb_controller",
          "pci"
        ],
        "bus_type": {
          "hex": "0004",
          "name": "PCI",
          "value": 4
        },
        "slot": {
          "bus": 0,
          "number": 29
        },
        "base_class": {
          "hex": "000c",
          "name": "Serial bus controller",
          "value": 12
        },
        "sub_class": {
          "hex": "0003",
          "name": "USB Controller",
          "value": 3
        },
        "pci_interface": {
          "hex": "0020",
          "name": "EHCI",
          "value": 32
        },
        "vendor": {
          "hex": "8086",
          "name": "Intel Corporation",
          "value": 32902
        },
        "sub_vendor": {
          "hex": "17aa",
          "value": 6058
        },
        "device": {
          "hex": "9ca6",
          "value": 40102
        },
        "sub_device": {
          "hex": "3987",
          "value": 14727
        },
        "revision": {
          "hex": "0003",
          "value": 3
        },
        "model": "Intel USB Controller",
        "sysfs_id": "/devices/pci0000:00/0000:00:1d.0",
        "sysfs_bus_id": "0000:00:1d.0",
        "resources": [
          {
            "type": "irq",
            "base": 23,
            "triggered": 0,
            "enabled": true
          },
          {
            "type": "mem",
            "base": 3240202240,
            "range": 1024,
            "enabled": true,
            "access": "read_write",
            "prefetch": "no"
          }
        ],
        "detail": {
          "function": 0,
          "command": 6,
          "header_type": 0,
          "secondary_bus": 0,
          "irq": 23,
          "prog_if": 32
        },
        "driver": "ehci-pci",
        "driver_module": "ehci_pci",
        "drivers": [
          "ehci-pci"
        ],
        "driver_modules": [
          "ehci_pci"
        ],
        "driver_info": {
          "type": "module",
          "db_entry_0": [
            "ehci-hcd"
          ],
          "active": true,
          "modprobe": true,
          "names": [
            "ehci-hcd"
          ],
          "module_args": [
            ""
          ],
          "conf": ""
        },
        "module_alias": "pci:v00008086d00009CA6sv000017AAsd00003987bc0Csc03i20"
      },
      {
        "index": 21,
        "attached_to": 0,
        "class_list": [
          "usb_controller",
          "pci"
        ],
        "bus_type": {
          "hex": "0004",
          "name": "PCI",
          "value": 4
        },
        "slot": {
          "bus": 0,
          "number": 20
        },
        "base_class": {
          "hex": "000c",
          "name": "Serial bus controller",
          "value": 12
        },
        "sub_class": {
          "hex": "0003",
          "name": "USB Controller",
          "value": 3
        },
        "pci_interface": {
          "hex": "0030",
          "value": 48
        },
        "vendor": {
          "hex": "8086",
          "name": "Intel Corporation",
          "value": 32902
        },
        "sub_vendor": {
          "hex": "17aa",
          "value": 6058
        },
        "device": {
          "hex": "9cb1",
          "value": 40113
        },
        "sub_device": {
          "hex": "3987",
          "value": 14727
        },
        "revision": {
          "hex": "0003",
          "value": 3
        },
        "model": "Intel USB Controller",
        "sysfs_id": "/devices/pci0000:00/0000:00:14.0",
        "sysfs_bus_id": "0000:00:14.0",
        "resources": [
          {
            "type": "irq",
            "base": 43,
            "triggered": 0,
            "enabled": true
          },
          {
            "type": "mem",
            "base": 3240099840,
            "range": 65536,
            "enabled": true,
            "access": "read_write",
            "prefetch": "no"
          }
        ],
        "detail": {
          "function": 0,
          "command": 1030,
          "header_type": 0,
          "secondary_bus": 0,
          "irq": 43,
          "prog_if": 48
        },
        "driver": "xhci_hcd",
        "driver_module": "xhci_pci",
        "drivers": [
          "xhci_hcd"
        ],
        "driver_modules": [
          "xhci_pci"
        ],
        "module_alias": "pci:v00008086d00009CB1sv000017AAsd00003987bc0Csc03i30"
      }
    ]
  },
  "smbios": {
    "bios": {
      "handle": 0,
      "vendor": "LENOVO",
      "version": "D1CN06WW",
      "date": "05/18/2015",
      "features": [
        "PCI supported",
        "BIOS flashable",
        "BIOS shadowing allowed",
        "CD boot supported",
        "Selectable boot supported",
        "EDD spec supported",
        "1.2MB NEC 9800 Japanese Floppy supported",
        "1.2MB Toshiba Japanese Floppy supported",
        "360kB Floppy supported",
        "1.2MB Floppy supported",
        "720kB Floppy supported",
        "2.88MB Floppy supported",
        "8042 Keyboard Services supported",
        "CGA/Mono Video supported",
        "ACPI supported",
        "USB Legacy supported",
        "BIOS Boot Spec supported"
      ],
      "start_address": "0xe0000",
      "rom_size": 6291456
    },
    "board": {
      "handle": 2,
      "manufacturer": "LENOVO",
      "product": "Lenovo B70-80",
      "version": "31900056 WIN",
      "board_type": {
        "hex": "000a",
        "name": "Motherboard",
        "value": 10
      },
      "features": [
        "Hosting Board",
        "Replaceable"
      ],
      "location": "Type2 - Board Chassis Location",
      "chassis": 3
    },
    "cache": [
      {
        "handle": 5,
        "socket": "L1 Cache",
        "size_max": 32,
        "size_current": 32,
        "speed": 0,
        "mode": {
          "hex": "0001",
          "name": "Write Back",
          "value": 1
        },
        "enabled": true,
        "location": {
          "hex": "0000",
          "name": "Internal",
          "value": 0
        },
        "socketed": false,
        "level": 0,
        "ecc": {
          "hex": "0004",
          "name": "Parity",
          "value": 4
        },
        "cache_type": {
          "hex": "0004",
          "name": "Data",
          "value": 4
        },
        "associativity": {
          "hex": "0007",
          "name": "8-way Set-Associative",
          "value": 7
        },
        "sram_type_current": [
          "Synchronous"
        ],
        "sram_type_supported": [
          "Synchronous"
        ]
      },
      {
        "handle": 6,
        "socket": "L1 Cache",
        "size_max": 32,
        "size_current": 32,
        "speed": 0,
        "mode": {
          "hex": "0001",
          "name": "Write Back",
          "value": 1
        },
        "enabled": true,
        "location": {
          "hex": "0000",
          "name": "Internal",
          "value": 0
        },
        "socketed": false,
        "level": 0,
        "ecc": {
          "hex": "0004",
          "name": "Parity",
          "value": 4
        },
        "cache_type": {
          "hex": "0003",
          "name": "Instruction",
          "value": 3
        },
        "associativity": {
          "hex": "0007",
          "name": "8-way Set-Associative",
          "value": 7
        },
        "sram_type_current": [
          "Synchronous"
        ],
        "sram_type_supported": [
          "Synchronous"
        ]
      },
      {
        "handle": 7,
        "socket": "L2 Cache",
        "size_max": 256,
        "size_current": 256,
        "speed": 0,
        "mode": {
          "hex": "0001",
          "name": "Write Back",
          "value": 1
        },
        "enabled": true,
        "location": {
          "hex": "0000",
          "name": "Internal",
          "value": 0
        },
        "socketed": false,
        "level": 1,
        "ecc": {
          "hex": "0005",
          "name": "Single-bit",
          "value": 5
        },
        "cache_type": {
          "hex": "0005",
          "name": "Unified",
          "value": 5
        },
        "associativity": {
          "hex": "0007",
          "name": "8-way Set-Associative",
          "value": 7
        },
        "sram_type_current": [
          "Synchronous"
        ],
        "sram_type_supported": [
          "Synchronous"
        ]
      },
      {
        "handle": 8,
        "socket": "L3 Cache",
        "size_max": 3072,
        "size_current": 3072,
        "speed": 0,
        "mode": {
          "hex": "0001",
          "name": "Write Back",
          "value": 1
        },
        "enabled": true,
        "location": {
          "hex": "0000",
          "name": "Internal",
          "value": 0
        },
        "socketed": false,
        "level": 2,
        "ecc": {
          "hex": "0006",
          "name": "Multi-bit",
          "value": 6
        },
        "cache_type": {
          "hex": "0005",
          "name": "Unified",
          "value": 5
        },
        "associativity": {
          "hex": "0009",
          "name": "Other",
          "value": 9
        },
        "sram_type_current": [
          "Synchronous"
        ],
        "sram_type_supported": [
          "Synchronous"
        ]
      }
    ],
    "chassis": [
      {
        "handle": 3,
        "manufacturer": "LENOVO",
        "version": "Lenovo B70-80",
        "chassis_type": {
          "hex": "000a",
          "name": "Notebook",
          "value": 10
        },
        "lock_present": false,
        "bootup_state": {
          "hex": "0003",
          "name": "Safe",
          "value": 3
        },
        "power_state": {
          "hex": "0003",
          "name": "Safe",
          "value": 3
        },
        "thermal_state": {
          "hex": "0003",
          "name": "Safe",
          "value": 3
        },
        "security_state": {
          "hex": "0003",
          "name": "None",
          "value": 3
        },
        "oem": "0x0"
      }
    ],
    "config": {
      "handle": 32,
      "options": [
        "ConfigOptions1",
        "ConfigOptions2",
        "ConfigOptions3"
      ]
    },
    "group_associations": [
      {
        "handle": 34,
        "name": "Firmware Version Info",
        "handles": [
          249108103227,
          244813135930,
          240518168633,
          236223201336,
          231928234039,
          210453397558
        ]
      },
      {
        "handle": 35,
        "name": "Intel(R) Silicon View Technology",
        "handles": [
          65
        ]
      },
      {
        "handle": 44,
        "power": {
          "hex": "0000",
          "name": "Disabled",
          "value": 0
        },
        "keyboard": {
          "hex": "0000",
          "name": "Disabled",
          "value": 0
        },
        "admin": {
          "hex": "0000",
          "name": "Disabled",
          "value": 0
        },
        "reset": {
          "hex": "0000",
          "name": "Disabled",
          "value": 0
        }
      }
    ],
    "language": [
      {
        "handle": 33,
        "languages": [
          "en|US|iso8859-1,0",
          "fr|CA|iso8859-1,0",
          "zh|TW|unicode,0",
          "ja|JP|unicode,0",
          "it|IT|iso8859-1,0",
          "es|ES|iso8859-1,0",
          "de|DE|iso8859-1,0",
          "pt|PT|iso8859-1,0"
        ]
      }
    ],
    "memory_array": [
      {
        "handle": 37,
        "location": {
          "hex": "0003",
          "name": "Motherboard",
          "value": 3
        },
        "usage": {
          "hex": "0003",
          "name": "System memory",
          "value": 3
        },
        "ecc": {
          "hex": "0003",
          "name": "None",
          "value": 3
        },
        "max_size": "0x1000000",
        "error_handle": 65535,
        "slots": 2
      }
    ],
    "memory_array_mapped_address": [
      {
        "handle": 40,
        "array_handle": 37,
        "start_address": "0x0",
        "end_address": "0x200000000",
        "part_width": 2
      }
    ],
    "memory_device": [
      {
        "handle": 38,
        "location": "ChannelA-DIMM0",
        "bank_location": "BANK 0",
        "manufacturer": "",
        "part_number": "",
        "array_handle": 37,
        "error_handle": 65535,
        "width": 0,
        "ecc_bits": 0,
        "size": 0,
        "form_factor": {
          "hex": "0009",
          "name": "DIMM",
          "value": 9
        },
        "set": 0,
        "memory_type": {
          "hex": "0002",
          "name": "Unknown",
          "value": 2
        },
        "memory_type_details": null,
        "speed": 0
      },
      {
        "handle": 39,
        "location": "ChannelB-DIMM0",
        "bank_location": "BANK 2",
        "manufacturer": "0467",
        "part_number": "RMT3160ME68FAF1600",
        "array_handle": 37,
        "error_handle": 65535,
        "width": 64,
        "ecc_bits": 0,
        "size": 8388608,
        "form_factor": {
          "hex": "000d",
          "name": "SODIMM",
          "value": 13
        },
        "set": 0,
        "memory_type": {
          "hex": "0018",
          "name": "Other",
          "value": 24
        },
        "memory_type_details": [
          "Synchronous"
        ],
        "speed": 1600
      }
    ],
    "memory_device_mapped_address": [
      {
        "handle": 41,
        "memory_device_handle": 39,
        "array_map_handle": 40,
        "start_address": "0x0",
        "end_address": "0x200000000",
        "row_position": 254,
        "interleave_position": 2,
        "interleave_depth": 1
      }
    ],
    "pointing_device": [
      {
        "handle": 42,
        "mouse_type": {
          "hex": "0007",
          "name": "Touch Pad",
          "value": 7
        },
        "interface": {
          "hex": "0004",
          "name": "PS/2",
          "value": 4
        },
        "buttons": 4
      }
    ],
    "port_connector": [
      {
        "handle": 9,
        "port_type": {
          "hex": "000d",
          "name": "Keyboard Port",
          "value": 13
        },
        "internal_reference_designator": "J1A1",
        "external_connector_type": {
          "hex": "000f",
          "name": "PS/2",
          "value": 15
        },
        "external_reference_designator": "Keyboard"
      },
      {
        "handle": 10,
        "port_type": {
          "hex": "000e",
          "name": "Mouse Port",
          "value": 14
        },
        "internal_reference_designator": "J1A1",
        "external_connector_type": {
          "hex": "000f",
          "name": "PS/2",
          "value": 15
        },
        "external_reference_designator": "Mouse"
      },
      {
        "handle": 11,
        "port_type": {
          "hex": "001c",
          "name": "Video Port",
          "value": 28
        },
        "internal_reference_designator": "J2A1",
        "external_connector_type": {
          "hex": "000d",
          "name": "Mini-DIN",
          "value": 13
        },
        "external_reference_designator": "TV OUT"
      },
      {
        "handle": 12,
        "port_type": {
          "hex": "001c",
          "name": "Video Port",
          "value": 28
        },
        "internal_reference_designator": "J2A2",
        "external_connector_type": {
          "hex": "0007",
          "name": "DB-15 pin female",
          "value": 7
        },
        "external_reference_designator": "CRT"
      },
      {
        "handle": 13,
        "port_type": {
          "hex": "0009",
          "name": "Serial Port 16550A Compatible",
          "value": 9
        },
        "internal_reference_designator": "J2A2",
        "external_connector_type": {
          "hex": "0008",
          "name": "DB-9 pin male",
          "value": 8
        },
        "external_reference_designator": "COM 1"
      },
      {
        "handle": 14,
        "port_type": {
          "hex": "0010",
          "name": "USB",
          "value": 16
        },
        "internal_reference_designator": "J3A1",
        "external_connector_type": {
          "hex": "0012",
          "name": "Access Bus [USB]",
          "value": 18
        },
        "external_reference_designator": "USB"
      },
      {
        "handle": 15,
        "port_type": {
          "hex": "0010",
          "name": "USB",
          "value": 16
        },
        "internal_reference_designator": "J3A1",
        "external_connector_type": {
          "hex": "0012",
          "name": "Access Bus [USB]",
          "value": 18
        },
        "external_reference_designator": "USB"
      },
      {
        "handle": 16,
        "port_type": {
          "hex": "0010",
          "name": "USB",
          "value": 16
        },
        "internal_reference_designator": "J3A1",
        "external_connector_type": {
          "hex": "0012",
          "name": "Access Bus [USB]",
          "value": 18
        },
        "external_reference_designator": "USB"
      },
      {
        "handle": 17,
        "port_type": {
          "hex": "0010",
          "name": "USB",
          "value": 16
        },
        "internal_reference_designator": "J5A1",
        "external_connector_type": {
          "hex": "0012",
          "name": "Access Bus [USB]",
          "value": 18
        },
        "external_reference_designator": "USB"
      },
      {
        "handle": 18,
        "port_type": {
          "hex": "0010",
          "name": "USB",
          "value": 16
        },
        "internal_reference_designator": "J5A1",
        "external_connector_type": {
          "hex": "0012",
          "name": "Access Bus [USB]",
          "value": 18
        },
        "external_reference_designator": "USB"
      },
      {
        "handle": 19,
        "port_type": {
          "hex": "0010",
          "name": "USB",
          "value": 16
        },
        "internal_reference_designator": "J5A2",
        "external_connector_type": {
          "hex": "0012",
          "name": "Access Bus [USB]",
          "value": 18
        },
        "external_reference_designator": "USB"
      },
      {
        "handle": 20,
        "port_type": {
          "hex": "001f",
          "name": "Network Port",
          "value": 31
        },
        "internal_reference_designator": "J5A1",
        "external_connector_type": {
          "hex": "000b",
          "name": "RJ-45",
          "value": 11
        },
        "external_reference_designator": "Network"
      },
      {
        "handle": 21,
        "port_type": {
          "hex": "00ff",
          "name": "Other",
          "value": 255
        },
        "internal_connector_type": {
          "hex": "0017",
          "name": "On Board Floppy",
          "value": 23
        },
        "internal_reference_designator": "J9G2",
        "external_reference_designator": "OnBoard Floppy Type"
      },
      {
        "handle": 22,
        "port_type": {
          "hex": "00ff",
          "name": "Other",
          "value": 255
        },
        "internal_connector_type": {
          "hex": "0016",
          "name": "On Board IDE",
          "value": 22
        },
        "internal_reference_designator": "J7J1",
        "external_reference_designator": "OnBoard Primary IDE"
      },
      {
        "handle": 23,
        "port_type": {
          "hex": "001d",
          "name": "Audio Port",
          "value": 29
        },
        "internal_reference_designator": "J30",
        "external_connector_type": {
          "hex": "001f",
          "name": "Mini-jack [headphones]",
          "value": 31
        },
        "external_reference_designator": "Microphone In"
      },
      {
        "handle": 24,
        "port_type": {
          "hex": "001d",
          "name": "Audio Port",
          "value": 29
        },
        "internal_reference_designator": "J30",
        "external_connector_type": {
          "hex": "001f",
          "name": "Mini-jack [headphones]",
          "value": 31
        },
        "external_reference_designator": "Line In"
      },
      {
        "handle": 25,
        "port_type": {
          "hex": "001d",
          "name": "Audio Port",
          "value": 29
        },
        "internal_reference_designator": "J30",
        "external_connector_type": {
          "hex": "001f",
          "name": "Mini-jack [headphones]",
          "value": 31
        },
        "external_reference_designator": "Speaker Out"
      }
    ],
    "processor": [
      {
        "handle": 4,
        "socket": "U3E1",
        "socket_type": {
          "hex": "002e",
          "name": "Other",
          "value": 46
        },
        "socket_populated": true,
        "manufacturer": "Intel(R) Corporation",
        "version": "Intel(R) Core(TM) i5-5200U CPU @ 2.20GHz",
        "part": "To Be Filled By O.E.M.",
        "processor_type": {
          "hex": "0003",
          "name": "CPU",
          "value": 3
        },
        "processor_family": {
          "hex": "00cd",
          "name": "Other",
          "value": 205
        },
        "processor_status": {
          "hex": "0001",
          "name": "Enabled",
          "value": 1
        },
        "clock_ext": 100,
        "clock_max": 2700,
        "cache_handle_l1": 6,
        "cache_handle_l2": 7,
        "cache_handle_l3": 8
      }
    ],
    "slot": [
      {
        "handle": 26,
        "designation": "J6C1",
        "slot_type": {
          "hex": "00a6",
          "name": "Other",
          "value": 166
        },
        "bus_width": {
          "hex": "0008",
          "name": "Other",
          "value": 8
        },
        "usage": {
          "hex": "0003",
          "name": "Available",
          "value": 3
        },
        "length": {
          "hex": "0001",
          "name": "Other",
          "value": 1
        },
        "id": 1,
        "features": [
          "PME#",
          "Hot-Plug"
        ]
      },
      {
        "handle": 27,
        "designation": "J6D2",
        "slot_type": {
          "hex": "00a6",
          "name": "Other",
          "value": 166
        },
        "bus_width": {
          "hex": "0008",
          "name": "Other",
          "value": 8
        },
        "usage": {
          "hex": "0003",
          "name": "Available",
          "value": 3
        },
        "length": {
          "hex": "0001",
          "name": "Other",
          "value": 1
        },
        "id": 2,
        "features": [
          "PME#",
          "Hot-Plug"
        ]
      },
      {
        "handle": 28,
        "designation": "J7C1",
        "slot_type": {
          "hex": "00a6",
          "name": "Other",
          "value": 166
        },
        "bus_width": {
          "hex": "0008",
          "name": "Other",
          "value": 8
        },
        "usage": {
          "hex": "0004",
          "name": "In Use",
          "value": 4
        },
        "length": {
          "hex": "0001",
          "name": "Other",
          "value": 1
        },
        "id": 3,
        "features": [
          "PME#",
          "Hot-Plug"
        ]
      },
      {
        "handle": 29,
        "designation": "J7D1",
        "slot_type": {
          "hex": "00a6",
          "name": "Other",
          "value": 166
        },
        "bus_width": {
          "hex": "0008",
          "name": "Other",
          "value": 8
        },
        "usage": {
          "hex": "0004",
          "name": "In Use",
          "value": 4
        },
        "length": {
          "hex": "0001",
          "name": "Other",
          "value": 1
        },
        "id": 4,
        "features": [
          "PME#",
          "Hot-Plug"
        ]
      },
      {
        "handle": 30,
        "designation": "J8C1",
        "slot_type": {
          "hex": "00a8",
          "name": "Other",
          "value": 168
        },
        "bus_width": {
          "hex": "000a",
          "name": "Other",
          "value": 10
        },
        "usage": {
          "hex": "0003",
          "name": "Available",
          "value": 3
        },
        "length": {
          "hex": "0001",
          "name": "Other",
          "value": 1
        },
        "id": 5,
        "features": [
          "PME#",
          "Hot-Plug"
        ]
      }
    ],
    "system": {
      "handle": 1,
      "manufacturer": "LENOVO",
      "product": "80MR",
      "version": "Lenovo B70-80",
      "wake_up": {
        "hex": "0006",
        "name": "Power Switch",
        "value": 6
      }
    }
  }
}
